pyapacheatlas/__init__.py
pyapacheatlas/__main__.py
pyapacheatlas/auth/__init__.py
pyapacheatlas/auth/azcredential.py
pyapacheatlas/auth/base.py
pyapacheatlas/auth/basic.py
pyapacheatlas/auth/serviceprincipal.py
pyapacheatlas/core/__init__.py
pyapacheatlas/core/client.py
pyapacheatlas/core/entity.py
pyapacheatlas/core/graphql.py
pyapacheatlas/core/msgraph.py
pyapacheatlas/core/typedef.py
pyapacheatlas/core/util.py
pyapacheatlas/core/whatif.py
pyapacheatlas/core/collections/__init__.py
pyapacheatlas/core/collections/purview.py
pyapacheatlas/core/discovery/__init__.py
pyapacheatlas/core/discovery/purview.py
pyapacheatlas/core/glossary/__init__.py
pyapacheatlas/core/glossary/glossaryclient.py
pyapacheatlas/core/glossary/term.py
pyapacheatlas/readers/__init__.py
pyapacheatlas/readers/excel.py
pyapacheatlas/readers/lineagemixin.py
pyapacheatlas/readers/reader.py
pyapacheatlas/readers/util.py
pyapacheatlas/scaffolding/__init__.py
pyapacheatlas/scaffolding/column_lineage.py
pyapacheatlas/scaffolding/entity_def.py
pyapacheatlas-0.16.0.dist-info/LICENSE
pyapacheatlas-0.16.0.dist-info/METADATA
pyapacheatlas-0.16.0.dist-info/WHEEL
pyapacheatlas-0.16.0.dist-info/top_level.txt
pyapacheatlas-0.16.0.dist-info/RECORD
