Metadata-Version: 2.1
Name: pyapacheatlas
Version: 0.16.0
Summary: A package to simplify working with the Apache Atlas REST APIs for Atlas and Azure Purview.
Home-page: https://github.com/wjohnson/pyapacheatlas
Author: Will Johnson
Author-email: will@willj.com
License: UNKNOWN
Platform: UNKNOWN
Classifier: Programming Language :: Python :: 3
Classifier: License :: OSI Approved :: MIT License
Classifier: Operating System :: OS Independent
Requires-Python: >=3.6
Requires-Dist: openpyxl >=3.0
Requires-Dist: requests >=2.0
